<?xml version="1.0"?>
<wikiPage>
  <title>Les elfes</title>
  <categories><category>Pathfinder-RPG.Advanced Player Guide</category><category>Pathfinder-RPG.Race</category></categories>
  <lastModified>2014-01-05 14:59:56Z</lastModified>
  <version>9</version>
  <inLinks><link>Pathfinder-RPG.Arc du long serment</link><link>Pathfinder-RPG.Archer-mage</link><link>Pathfinder-RPG.Art de la magie</link><link>Pathfinder-RPG.Bottes elfiques</link><link>Pathfinder-RPG.Cape elfique</link><link>Pathfinder-RPG.Caractéristiques des armures</link><link>Pathfinder-RPG.Cartes fantasmagoriques</link><link>Pathfinder-RPG.Coup de flèche</link><link>Pathfinder-RPG.Créer des PNJ</link><link>Pathfinder-RPG.Demi-elfe</link><link>Pathfinder-RPG.Demi-orque</link><link>Pathfinder-RPG.Déplacement et position</link><link>Pathfinder-RPG.dons raciaux</link><link>Pathfinder-RPG.Elfe</link><link>Pathfinder-RPG.État civil et mensurations</link><link>Pathfinder-RPG.Expériences variées</link><link>Pathfinder-RPG.Exploration</link><link>Pathfinder-RPG.FAQ Bestiaire</link><link>Pathfinder-RPG.FAQ Classes</link><link>Pathfinder-RPG.FAQ Magie</link><link>Pathfinder-RPG.FAQ Races</link><link>Pathfinder-RPG.Halfelin</link><link>Pathfinder-RPG.Humain</link><link>Pathfinder-RPG.Linguistique</link><link>Pathfinder-RPG.Main du mage</link><link>Pathfinder-RPG.MainPage</link><link>Pathfinder-RPG.Mauvais œil</link><link>Pathfinder-RPG.Montures et harnachement</link><link>Pathfinder-RPG.Nain</link><link>Pathfinder-RPG.Objets intelligents</link><link>Pathfinder-RPG.Pas léger</link><link>Pathfinder-RPG.Perception</link><link>Pathfinder-RPG.Précision elfique</link><link>Pathfinder-RPG.Races</link><link>Pathfinder-RPG.Réincarnation</link><link>Pathfinder-RPG.Rôdeur infiltré (rôdeur)</link><link>Pathfinder-RPG.sort Cauchemar</link><link>Pathfinder-RPG.Tableau récapitulatif des dons</link><link>Pathfinder-RPG.Talent magique</link><link>Pathfinder-RPG.Valeurs de combat</link></inLinks>
  <outLinks><link>Pathfinder-RPG.Nain</link><link>Pathfinder-RPG.Gnome</link><link>Pathfinder-RPG.Halfelin</link><link>Pathfinder-RPG.Humain</link><link>Pathfinder-RPG.Demi-elfe</link><link>Pathfinder-RPG.Demi-orque</link><link>Pathfinder-RPG.Alignement</link><link>Pathfinder-RPG.CB</link><link>Pathfinder-RPG.Magicien</link><link>Pathfinder-RPG.Rôdeur</link><link>Pathfinder-RPG.Dextérité</link><link>Pathfinder-RPG.Intelligence</link><link>Pathfinder-RPG.Constitution</link><link>Pathfinder-RPG.taille M</link><link>Pathfinder-RPG.vitesse de déplacement</link><link>Pathfinder-RPG.vision nocturne</link><link>Pathfinder-RPG.jet de sauvegarde</link><link>Pathfinder-RPG.Enchantement</link><link>Pathfinder-RPG.NLS</link><link>Pathfinder-RPG.RM</link><link>Pathfinder-RPG.Art de la magie</link><link>Pathfinder-RPG.Perception</link><link>Pathfinder-RPG.arme de guerre</link><link>Pathfinder-RPG.Linguistique</link><link>Pathfinder-RPG.États préjudiciables</link><link>Pathfinder-RPG.Capacités spéciales</link><link>Pathfinder-RPG.Lumière</link><link>Pathfinder-RPG.Discrétion</link><link>Pathfinder-RPG.Valeurs de combat</link><link>Pathfinder-RPG.Natation</link><link>Pathfinder-RPG.Compétences</link><link>Pathfinder-RPG.Vocabulaire courant</link><link>Pathfinder-RPG.Divination (école)</link><link>Pathfinder-RPG.Charisme</link><link>Pathfinder-RPG.Songe</link><link>Pathfinder-RPG.Lancer des sorts</link><link>Pathfinder-RPG.Orque</link><link>Pathfinder-RPG.Connaissances</link><link>Pathfinder-RPG.Survie</link><link>Pathfinder-RPG.Progression des personnages</link><link>Pathfinder-RPG.Alchimiste</link><link>Pathfinder-RPG.Barbare</link><link>Pathfinder-RPG.Elfe</link><link>Pathfinder-RPG.Barde</link><link>Pathfinder-RPG.Guerrier</link><link>Pathfinder-RPG.DMD</link><link>Pathfinder-RPG.Manœuvres offensives</link><link>Pathfinder-RPG.Chevalier</link><link>Pathfinder-RPG.Conjurateur</link><link>Pathfinder-RPG.Ensorceleur</link><link>Pathfinder-RPG.eidolon</link><link>Pathfinder-RPG.Druide</link><link>Pathfinder-RPG.Lignages</link><link>Pathfinder-RPG.Inquisiteur</link><link>Pathfinder-RPG.jugements</link><link>Pathfinder-RPG.Écoles de magie</link><link>Pathfinder-RPG.Moine</link><link>Pathfinder-RPG.Oracle</link><link>Pathfinder-RPG.mystères</link><link>Pathfinder-RPG.Paladin</link><link>Pathfinder-RPG.Prêtre</link><link>Pathfinder-RPG.Actions simples</link><link>Pathfinder-RPG.Don pour les critiques</link><link>Pathfinder-RPG.Roublard</link><link>Pathfinder-RPG.Sorcière</link><link>Pathfinder-RPG.maléfices</link><link>Pathfinder-RPG.Familiers</link></outLinks>
  <body><![CDATA[&lt;i&gt;Les elfes sont des cr&#233;atures de la nature qui poss&#232;dent de nombreux points communs (et quelques diff&#233;rences) avec les cr&#233;atures f&#233;eriques. Les elfes accordent beaucoup d’importance &#224; l’intimit&#233; et aux traditions. Ils n’accordent pas leur amiti&#233; rapidement mais, lorsqu’un elfe ou une communaut&#233; d’elfes consid&#232;re un &#233;tranger comme un camarade, cette alliance peut perdurer sur plusieurs g&#233;n&#233;rations. &#192; cause de leur esp&#233;rance de vie incroyablement longue ou peut-&#234;tre pour des raisons plus mystiques, les elfes poss&#232;dent une relation &#233;trange avec leur environnement. Ceux qui r&#233;sident dans une r&#233;gion pendant une longue p&#233;riode subissent une adaptation physique &#224; leur milieu, dont l’aspect le plus flagrant est un changement de couleur de peau. De leur c&#244;t&#233;, les elfes qui passent leur vie au sein des autres races &#224; moindre esp&#233;rance de vie d&#233;veloppent souvent une perception fauss&#233;e de la mortalit&#233; et deviennent moroses apr&#232;s avoir assist&#233; de mani&#232;re r&#233;p&#233;t&#233;e au vieillissement et &#224; la mort de leurs compagnons.&lt;/i&gt;&lt;br /&gt;&lt;br /&gt;&lt;div class=&quot;presentation arrondi&quot;&gt;
Connus pour leur gr&#226;ce, leur sagesse et leur quasi-immortalit&#233;, les elfes sont tenus en haute estime par la plupart des autres races, tout sp&#233;cialement pour leur ma&#238;trise de la magie et leur savoir encyclop&#233;dique. Cependant, les membres de cette race se sentent souvent cern&#233;s de toutes parts et isol&#233;s par des races plus jeunes, plus agressives et comptant beaucoup plus d’individus qu’eux. Malgr&#233; tout, les aventuriers elfes qui ont &#233;t&#233; &#233;lev&#233;s et ont grandi dans des enclaves elfiques qui, bien souvent, incarnent
la beaut&#233; et l’esprit de leur environnement, emportent avec eux la force et la gloire de la culture elfique et les r&#233;pandent dans le monde, souvent par l’&#233;p&#233;e ou &#224; l’aide de la magie. La vision classique des elfes en tant que protecteurs des for&#234;ts est correcte mais incompl&#232;te : les elfes s’adaptent facilement &#224; de nombreux environnements pouvant aller des d&#233;serts les plus inhospitaliers aux profondeurs de la mer. D’autres s’int&#233;ressent aux myst&#232;res et &#224; la magie de certains domaines que leurs
fr&#232;res et soeurs ignorent. Ces elfes poss&#232;dent des traits raciaux diff&#233;rents de ceux dont jouissent les individus &#233;lev&#233;s dans un style de vie elfique plus traditionnel.
&lt;/div&gt;&lt;br /&gt;&lt;b&gt;Description physique.&lt;/b&gt; Les elfes sont g&#233;n&#233;ralement plus grands que les humains, mais aussi plus gracieux et plus fragiles (une apparence que leurs longues oreilles pointues accentuent). Ils poss&#232;dent de larges yeux en forme d’amande et de grandes pupilles de couleur vive. Les elfes se parent g&#233;n&#233;ralement d’habits qui rappellent la beaut&#233; de la nature, mais ceux qui vivent en ville s’habillent plut&#244;t selon la mode en vogue.&lt;br /&gt;&lt;br /&gt;&lt;b&gt;Soci&#233;t&#233;.&lt;/b&gt; De nombreux elfes se sentent fortement li&#233;s &#224; la nature et tentent de vivre en harmonie avec elle. Le travail de la terre et de la pierre n’en attire cependant pas beaucoup : ils pr&#233;f&#232;rent s’adonner &#224; des arts plus raffin&#233;s. Leur patience inn&#233;e les destine naturellement &#224; une carri&#232;re dans les arts magiques.&lt;br /&gt;&lt;br /&gt;&lt;b&gt;Relations.&lt;/b&gt; Les elfes ont tendance &#224; consid&#233;rer les autres races comme trop impulsives et irr&#233;fl&#233;chies et &#224; les rejeter. Ils sont cependant tr&#232;s dou&#233;s pour cerner les personnalit&#233;s et les qualit&#233;s. Un elfe &#233;vitera de prendre un &lt;a class=&quot;pagelink&quot; href=&quot;Nain.html&quot; title=&quot;Les nains&quot;&gt;nain&lt;/a&gt; pour voisin mais il sera le premier &#224; reconna&#238;tre son habilet&#233; &#224; la forge. Ils voient les &lt;a class=&quot;pagelink&quot; href=&quot;Gnome.html&quot; title=&quot;Les gnomes&quot;&gt;gnomes&lt;/a&gt; comme des curiosit&#233;s &#233;tranges (et parfois m&#234;me dangereuses) et &#233;prouvent une certaine piti&#233; envers les &lt;a class=&quot;pagelink&quot; href=&quot;Halfelin.html&quot; title=&quot;Les halfelins&quot;&gt;halfelins&lt;/a&gt; car les petites gens leur semblent d&#233;pourvus d’attaches et de foyer originel. Les &lt;a class=&quot;pagelink&quot; href=&quot;Humain.html&quot; title=&quot;Les humains&quot;&gt;humains&lt;/a&gt;, quant &#224; eux, fascinent les elfes. Le nombre important de &lt;a class=&quot;pagelink&quot; href=&quot;Demi-Elfe.html&quot; title=&quot;Les demi-elfes&quot;&gt;demi-elfes&lt;/a&gt; en est la preuve, m&#234;me si les elfes ne s’attachent g&#233;n&#233;ralement pas &#224; leurs descendants. Quant aux &lt;a class=&quot;pagelink&quot; href=&quot;Demi-Orque.html&quot; title=&quot;Les demi-orques&quot;&gt;demi-orques&lt;/a&gt;, ils leur inspirent de la m&#233;fiance.&lt;br /&gt;&lt;br /&gt;&lt;b&gt;Alignement et religion.&lt;/b&gt; Les elfes se laissent guider par les &#233;motions et les caprices mais ils accordent une grande importance &#224; la gentillesse et &#224; la beaut&#233;. La plupart des elfes sont d’&lt;a class=&quot;pagelink&quot; href=&quot;Alignement.html&quot; title=&quot;L&amp;#39;alignement&quot;&gt;alignement&lt;/a&gt; &lt;a class=&quot;pagelink&quot; href=&quot;Alignement.html#CB&quot; title=&quot;CB&quot;&gt;Chaotique Bon&lt;/a&gt;. Ils pr&#233;f&#232;rent les dieux qui partagent leur amour du mysticisme.&lt;br /&gt;&lt;br /&gt;&lt;b&gt;Aventuriers.&lt;/b&gt; La plupart des elfes qui partent &#224; l’aventure sont mus par le d&#233;sir d’explorer le monde. Ils quittent leurs royaumes forestiers isol&#233;s &#224; la recherche d’anciennes magies elfiques ou des empires oubli&#233;s fond&#233;s par leurs anc&#234;tres des mill&#233;naires plus t&#244;t. Le c&#244;t&#233; &#233;ph&#233;m&#232;re de la vie d’aventurier et la libert&#233; qui la caract&#233;rise attirent naturellement les elfes qui ont &#233;t&#233; &#233;lev&#233;s au sein des communaut&#233;s humaines. &#192; cause de leur fragilit&#233; physique, les elfes &#233;vitent g&#233;n&#233;ralement le combat au corps &#224; corps et pr&#233;f&#232;rent se tourner vers des classes comme &lt;a class=&quot;pagelink&quot; href=&quot;Magicien.html&quot; title=&quot;Le magicien&quot;&gt;magicien&lt;/a&gt; ou &lt;a class=&quot;pagelink&quot; href=&quot;R&#244;deur.html&quot; title=&quot;Le r&#244;deur&quot;&gt;r&#244;deur&lt;/a&gt;.&lt;br /&gt;&lt;br /&gt;&lt;h2 class=&quot;separator&quot;&gt;Les traits raciaux des elfes&lt;a class=&quot;headeranchor&quot; id=&quot;Les_traits_raciaux_des_elfes_0&quot; href=&quot;#Les_traits_raciaux_des_elfes_0&quot; title=&quot;Link to this Section&quot; style=&quot;visibility: hidden;&quot;&gt;&amp;nbsp;&lt;/a&gt;&lt;/h2&gt;
&lt;table class=&quot;page espace-col deuxcol&quot;&gt;
&lt;tr style=&quot;vertical-align: top&quot;&gt;&lt;td&gt;
&lt;div class=&quot;presentation arrondi ombre espaceliste&quot;&gt;
&lt;h2 class=&quot;separator&quot;&gt;Traits raciaux des elfes&lt;a class=&quot;headeranchor&quot; id=&quot;Traits_raciaux_des_elfes_1&quot; href=&quot;#Traits_raciaux_des_elfes_1&quot; title=&quot;Link to this Section&quot; style=&quot;visibility: hidden;&quot;&gt;&amp;nbsp;&lt;/a&gt;&lt;/h2&gt;
&lt;ul&gt;&lt;li&gt;&lt;b&gt;+2 &lt;a class=&quot;pagelink&quot; href=&quot;Caract&#233;ristiques.html#DEXTERITE&quot; title=&quot;La Dext&#233;rit&#233;&quot;&gt;Dext&#233;rit&#233;&lt;/a&gt;, +2 &lt;a class=&quot;pagelink&quot; href=&quot;Caract&#233;ristiques.html#INTELLIGENCE&quot; title=&quot;L&amp;#39;Intelligence&quot;&gt;Intelligence&lt;/a&gt;, -2 &lt;a class=&quot;pagelink&quot; href=&quot;Caract&#233;ristiques.html#CONSTITUTION&quot; title=&quot;La Constitution&quot;&gt;Constitution&lt;/a&gt;.&lt;/b&gt; Les elfes sont agiles, tant physiquement que mentalement, mais plut&#244;t fr&#234;les.&lt;/li&gt;&lt;li&gt;&lt;b&gt;Taille moyenne.&lt;/b&gt; Les elfes sont des cr&#233;atures de &lt;a class=&quot;pagelink&quot; href=&quot;Petites-Et-Grandes-Cr&#233;atures.html#TABLEAUTAILLES&quot; title=&quot;taille M&quot;&gt;taille M&lt;/a&gt;, ce qui ne leur apporte aucun bonus ni malus de taille.&lt;br /&gt;&lt;a name=&quot;VITESSENORMALE&quot;&gt;&lt;/a&gt;&lt;/li&gt;&lt;li&gt;&lt;b&gt;Vitesse normale.&lt;/b&gt; Les elfes poss&#232;dent une &lt;a class=&quot;pagelink&quot; href=&quot;Valeurs-De-Combat.html#VITESSEDEDEPLACEMENT&quot; title=&quot;vitesse de d&#233;placement&quot;&gt;vitesse de d&#233;placement&lt;/a&gt; de base de 9 m&#232;tres (6 cases).&lt;/li&gt;&lt;li&gt;&lt;b&gt;&lt;a class=&quot;pagelink&quot; href=&quot;Vision-Nocturne-(Capacit&#233;).html&quot; title=&quot;vision nocturne&quot;&gt;Vision nocturne&lt;/a&gt;.&lt;/b&gt; Les elfes peuvent voir deux fois plus loin que les humains dans des conditions de faible &#233;clairage.&lt;/li&gt;&lt;li&gt;&lt;b&gt;Immunit&#233;s elfiques.&lt;/b&gt; Les elfes sont immunis&#233;s aux effets de sommeil magique et b&#233;n&#233;ficient d’un bonus racial de +2 aux &lt;a class=&quot;pagelink&quot; href=&quot;Valeurs-De-Combat.html#JETDESAUVEGARDE&quot; title=&quot;jet de sauvegarde&quot;&gt;jets de sauvegarde&lt;/a&gt; contre les sorts et les effets de type &lt;a class=&quot;pagelink&quot; href=&quot;Pr&#233;sentation-Des-Sorts.html#ENCHANTEMENT&quot; title=&quot;Enchantement&quot;&gt;enchantement&lt;/a&gt;.&lt;/li&gt;&lt;li&gt;&lt;b&gt;Magie elfique.&lt;/b&gt; Les elfes re&#231;oivent un bonus racial de +2 aux tests de &lt;a class=&quot;pagelink&quot; href=&quot;Lancer-Des-Sorts.html#NLS&quot; title=&quot;NLS&quot;&gt;niveau de lanceur de sorts&lt;/a&gt; pour surmonter la &lt;a class=&quot;pagelink&quot; href=&quot;R&#233;sistance-&#192;-La-Magie-(Capacit&#233;).html&quot; title=&quot;RM&quot;&gt;r&#233;sistance &#224; la magie&lt;/a&gt; des cibles. Ils re&#231;oivent &#233;galement un bonus racial de +2 aux tests d’&lt;a class=&quot;pagelink&quot; href=&quot;Art-De-La-Magie.html&quot; title=&quot;Art de la magie&quot;&gt;Art de la magie&lt;/a&gt; pour identifier les propri&#233;t&#233;s des objets magiques.&lt;/li&gt;&lt;li&gt;&lt;b&gt;Sens aiguis&#233;s.&lt;/b&gt; Les elfes re&#231;oivent un bonus racial de +2 aux tests de &lt;a class=&quot;pagelink&quot; href=&quot;Perception.html&quot; title=&quot;Perception&quot;&gt;Perception&lt;/a&gt;.&lt;/li&gt;&lt;li&gt;&lt;b&gt;Armes famili&#232;res.&lt;/b&gt; Les elfes sont form&#233;s au maniement des arcs longs (y compris les arcs longs composites), des arcs courts (y compris les arcs courts composites), des &#233;p&#233;es longues, des rapi&#232;res et ils consid&#232;rent toutes les armes dont le nom comporte le mot &#171; elfe &#187; ou &#171; elfique &#187; comme des &lt;a class=&quot;pagelink&quot; href=&quot;Caract&#233;ristiques-Des-Armes.html#ARMEDEGUERRE&quot; title=&quot;arme de guerre&quot;&gt;armes de guerre&lt;/a&gt;.&lt;/li&gt;&lt;li&gt;&lt;b&gt;Langues suppl&#233;mentaires.&lt;/b&gt; Les elfes connaissent automatiquement le &lt;a class=&quot;pagelink&quot; href=&quot;Linguistique.html&quot; title=&quot;Linguistique&quot;&gt;commun&lt;/a&gt; et l’&lt;a class=&quot;pagelink&quot; href=&quot;Linguistique.html&quot; title=&quot;Linguistique&quot;&gt;elfe&lt;/a&gt;. Les elfes poss&#233;dant une &lt;a class=&quot;pagelink&quot; href=&quot;Caract&#233;ristiques.html#INTELLIGENCE&quot; title=&quot;L&amp;#39;Intelligence&quot;&gt;Intelligence&lt;/a&gt; &#233;lev&#233;e peuvent choisir d’&lt;a class=&quot;pagelink&quot; href=&quot;Linguistique.html&quot; title=&quot;Linguistique&quot;&gt;autres langues&lt;/a&gt; parmi la liste suivante : &lt;a class=&quot;pagelink&quot; href=&quot;Linguistique.html&quot; title=&quot;Linguistique&quot;&gt;c&#233;leste&lt;/a&gt;, &lt;a class=&quot;pagelink&quot; href=&quot;Linguistique.html&quot; title=&quot;Linguistique&quot;&gt;draconien&lt;/a&gt;, &lt;a class=&quot;pagelink&quot; href=&quot;Linguistique.html&quot; title=&quot;Linguistique&quot;&gt;gnoll&lt;/a&gt;, &lt;a class=&quot;pagelink&quot; href=&quot;Linguistique.html&quot; title=&quot;Linguistique&quot;&gt;gnome&lt;/a&gt;, &lt;a class=&quot;pagelink&quot; href=&quot;Linguistique.html&quot; title=&quot;Linguistique&quot;&gt;gobelin&lt;/a&gt;, &lt;a class=&quot;pagelink&quot; href=&quot;Linguistique.html&quot; title=&quot;Linguistique&quot;&gt;orque&lt;/a&gt; et &lt;a class=&quot;pagelink&quot; href=&quot;Linguistique.html&quot; title=&quot;Linguistique&quot;&gt;sylvestre&lt;/a&gt;.&lt;br /&gt;&lt;/li&gt;&lt;/ul&gt;&lt;br /&gt;&lt;/div&gt;
&lt;/td&gt;&lt;td&gt;
&lt;div class=&quot;presentation arrondi ombre espaceliste&quot;&gt;
&lt;h2 class=&quot;separator&quot;&gt;Traits alternatifs&lt;a class=&quot;headeranchor&quot; id=&quot;Traits_alternatifs_2&quot; href=&quot;#Traits_alternatifs_2&quot; title=&quot;Link to this Section&quot; style=&quot;visibility: hidden;&quot;&gt;&amp;nbsp;&lt;/a&gt;&lt;/h2&gt;&lt;ul&gt;&lt;li&gt;&lt;b&gt;Agent de la lumi&#232;re.&lt;/b&gt; Certains elfes v&#233;n&#232;rent le soleil, la lune et les &#233;toiles, mais d’autres sont litt&#233;ralement touch&#233;s par le pouvoir radieux des cieux. Les elfes disposant de ce trait racial sont immunis&#233;s contre l’&lt;a class=&quot;pagelink&quot; href=&quot;&#201;tats-Pr&#233;judiciables.html#Aveugl&#233;&quot; title=&quot;&#201;tats pr&#233;judiciables&quot;&gt;aveuglement&lt;/a&gt; par la lumi&#232;re et les effets &lt;a class=&quot;pagelink&quot; href=&quot;&#201;tats-Pr&#233;judiciables.html#&#201;bloui&quot; title=&quot;&#201;tats pr&#233;judiciables&quot;&gt;&#233;blouissants&lt;/a&gt;. De plus, lorsqu’ils lancent des sorts ou des effets bas&#233;s sur la lumi&#232;re (y compris les &lt;a class=&quot;pagelink&quot; href=&quot;Capacit&#233;s-Sp&#233;ciales.html#TYPES&quot; title=&quot;Les capacit&#233;s sp&#233;ciales&quot;&gt;pouvoirs magiques&lt;/a&gt; et les &lt;a class=&quot;pagelink&quot; href=&quot;Capacit&#233;s-Sp&#233;ciales.html#TYPES&quot; title=&quot;Les capacit&#233;s sp&#233;ciales&quot;&gt;capacit&#233;s surnaturelles&lt;/a&gt;), les variables de ceux-ci sont d&#233;termin&#233;es comme s’ils avaient un niveau de plus. Les elfes poss&#233;dant une &lt;a class=&quot;pagelink&quot; href=&quot;Caract&#233;ristiques.html#INTELLIGENCE&quot; title=&quot;L&amp;#39;Intelligence&quot;&gt;Intelligence&lt;/a&gt; sup&#233;rieure ou &#233;gale &#224; 10 peuvent utiliser &lt;a class=&quot;pagelink&quot; href=&quot;Lumi&#232;re.html&quot; title=&quot;Lumi&#232;re&quot;&gt;lumi&#232;re&lt;/a&gt; &#224; volont&#233; en tant que &lt;a class=&quot;pagelink&quot; href=&quot;Capacit&#233;s-Sp&#233;ciales.html#types&quot; title=&quot;Les capacit&#233;s sp&#233;ciales&quot;&gt;pouvoir magique&lt;/a&gt;. Ce trait racial remplace Immunit&#233;s elfiques et Magie elfique.&lt;/li&gt;&lt;li&gt;&lt;b&gt;Chasseur silencieux.&lt;/b&gt; Les elfes sont r&#233;put&#233;s pour leur subtilit&#233; et leurs prouesses. Les elfes disposant de ce trait racial r&#233;duisent de 5 la p&#233;nalit&#233; impos&#233;e aux tests de &lt;a class=&quot;pagelink&quot; href=&quot;Discr&#233;tion.html&quot; title=&quot;Discr&#233;tion&quot;&gt;Discr&#233;tion&lt;/a&gt; effectu&#233;s au cours d’un d&#233;placement et peuvent effectuer de tels tests m&#234;me en courant, avec une p&#233;nalit&#233; de -20 (ce nombre inclut la r&#233;duction de p&#233;nalit&#233; offerte par ce trait). Ce trait racial remplace Magie elfique.&lt;/li&gt;&lt;li&gt;&lt;b&gt;Coureur du d&#233;sert.&lt;/b&gt; Certains elfes s’efforcent de survivre dans les profondeurs du d&#233;sert o&#249; ils ne cessent de parcourir des terres br&#251;l&#233;es et dess&#233;ch&#233;es. Les elfes disposant de ce trait racial gagnent un bonus racial de +4 aux tests de &lt;a class=&quot;pagelink&quot; href=&quot;Caract&#233;ristiques.html#CONSTITUTION&quot; title=&quot;La Constitution&quot;&gt;Constitution&lt;/a&gt; et aux jets de &lt;a class=&quot;pagelink&quot; href=&quot;Valeurs-De-Combat.html#JETDESAUVEGARDE&quot; title=&quot;Valeurs de combat&quot;&gt;Vigueur&lt;/a&gt; pour &#233;viter la fatigue, l’&#233;puisement ou les autres effets n&#233;gatifs de la course, des marches forc&#233;es, de la faim, de la soif et des environnements chauds ou froids. Ce trait racial remplace Magie elfique.&lt;/li&gt;&lt;li&gt;&lt;b&gt;Esprit des eaux.&lt;/b&gt; Certains elfes se sont adapt&#233;s &#224; une vie en harmonie avec la mer ou les profondeurs des rivi&#232;res et des lacs sauvages. Ils gagnent un bonus racial de +4 aux tests de &lt;a class=&quot;pagelink&quot; href=&quot;Natation.html&quot; title=&quot;Natation&quot;&gt;Natation&lt;/a&gt;, peuvent toujours &lt;a class=&quot;pagelink&quot; href=&quot;Comp&#233;tences.html#FAIRE10&quot; title=&quot;Les comp&#233;tences&quot;&gt;&#171; faire 10 &#187;&lt;/a&gt; pour nager et peuvent choisir l’aquatique comme &lt;a class=&quot;pagelink&quot; href=&quot;Linguistique.html&quot; title=&quot;Linguistique&quot;&gt;langue suppl&#233;mentaire&lt;/a&gt;. Ils sont form&#233;s au maniement de la pique, du trident et du filet. Ce trait racial remplace Magie elfique et Armes famili&#232;res.&lt;/li&gt;&lt;li&gt;&lt;b&gt;Murmures des r&#234;ves.&lt;/b&gt; Certains elfes sont capables d’utiliser le pouvoir du sommeil, des r&#234;ves et de la r&#234;verie pr&#233;cognitive. Les elfes disposant de ce trait racial ajoutent +1 aux &lt;a class=&quot;pagelink&quot; href=&quot;Vocabulaire-Courant.html#DEGREDEDIFFICULTE&quot; title=&quot;Vocabulaire courant&quot;&gt;DD&lt;/a&gt; des &lt;a class=&quot;pagelink&quot; href=&quot;Valeurs-De-Combat.html#JETDESAUVEGARDE&quot; title=&quot;Valeurs de combat&quot;&gt;jets de sauvegarde&lt;/a&gt; des sorts de l’&lt;a class=&quot;pagelink&quot; href=&quot;Divination-(&#201;cole).html&quot; title=&quot;L&amp;#39;&#233;cole de Divination&quot;&gt;&#233;cole de Divination&lt;/a&gt; et des effets de sommeil qu’ils lancent. De plus, ceux qui poss&#232;dent un &lt;a class=&quot;pagelink&quot; href=&quot;Caract&#233;ristiques.html#CHARISME&quot; title=&quot;Le Charisme&quot;&gt;Charisme&lt;/a&gt; sup&#233;rieur ou &#233;gal &#224; 15 peuvent utiliser &lt;a class=&quot;pagelink&quot; href=&quot;Songe.html&quot; title=&quot;Songe&quot;&gt;songe&lt;/a&gt; une fois par jour sous la forme d’un &lt;a class=&quot;pagelink&quot; href=&quot;Capacit&#233;s-Sp&#233;ciales.html#TYPES&quot; title=&quot;Les capacit&#233;s sp&#233;ciales&quot;&gt;pouvoir magique&lt;/a&gt; dont le &lt;a class=&quot;pagelink&quot; href=&quot;Lancer-Des-Sorts.html#NLS&quot; title=&quot;Lancer des sorts&quot;&gt;NLS&lt;/a&gt; est &#233;gal au niveau de personnage. Ce trait racial remplace Immunit&#233;s elfiques.&lt;/li&gt;&lt;li&gt;&lt;b&gt;Rancune &#233;ternelle.&lt;/b&gt; Les elfes disposant de ce trait racial ont grandi dans des communaut&#233;s isol&#233;es et isolationnistes o&#249; des querelles datant de plusieurs g&#233;n&#233;rations ont donn&#233; naissance &#224; des conflits sanglants perp&#233;tuels. Ils re&#231;oivent un bonus de +1 aux &lt;a class=&quot;pagelink&quot; href=&quot;Valeurs-De-Combat.html#JETDATTAQUE&quot; title=&quot;Valeurs de combat&quot;&gt;jets d’attaque&lt;/a&gt; contre les humano&#239;des des sous-types &lt;a class=&quot;pagelink&quot; href=&quot;Nain.html&quot; title=&quot;Les nains&quot;&gt;nain&lt;/a&gt; et &lt;a class=&quot;pagelink&quot; href=&quot;Orque.html&quot; title=&quot;Orque&quot;&gt;orque&lt;/a&gt; gr&#226;ce &#224; un entra&#238;nement sp&#233;cial contre ces adversaires. Ce trait racial remplace&lt;br /&gt;Magie elfique.&lt;/li&gt;&lt;li&gt;&lt;b&gt;Travail du bois.&lt;/b&gt; Les elfes connaissent mieux que quiconque les secrets des contr&#233;es sauvages et plus particuli&#232;rement des for&#234;ts. Les elfes disposant de ce trait racial gagnent un bonus de +1 aux tests de &lt;a class=&quot;pagelink&quot; href=&quot;Connaissances.html&quot; title=&quot;Connaissances&quot;&gt;Connaissances&lt;/a&gt; (nature) et aux tests de &lt;a class=&quot;pagelink&quot; href=&quot;Survie.html&quot; title=&quot;Survie&quot;&gt;Survie&lt;/a&gt;. En for&#234;t, ces bonus passent &#224; +2. Ce trait racial remplace Magie elfique.&lt;br /&gt;&lt;/li&gt;&lt;/ul&gt;&lt;br /&gt;&lt;/div&gt;
&lt;/td&gt;&lt;/tr&gt;&lt;/table&gt;&lt;br /&gt;
&lt;h2 class=&quot;separator&quot;&gt; Les aventuriers elfes &lt;a class=&quot;headeranchor&quot; id=&quot;Les_aventuriers_elfes_3&quot; href=&quot;#Les_aventuriers_elfes_3&quot; title=&quot;Link to this Section&quot; style=&quot;visibility: hidden;&quot;&gt;&amp;nbsp;&lt;/a&gt;&lt;/h2&gt;
Les elfes qui choisissent de devenir aventuriers suivent g&#233;n&#233;ralement la voie du combattant, cherchent &#224; ma&#238;triser la magie profane ou optent pour une carri&#232;re qui m&#233;langent les deux. Les elfes pr&#233;f&#232;rent la subtilit&#233; au conflit ouvert mais ils aiment d&#233;montrer leur sup&#233;riorit&#233; aux autres races, quitte &#224; employer la force si la finesse et le panache ne suffisent pas.&lt;br /&gt;&lt;br /&gt;&lt;i&gt;Bonus de classe de pr&#233;dilection alternatif:&lt;/i&gt; Plut&#244;t que de gagner un point de vie ou un point de comp&#233;tence suppl&#233;mentaire lorsqu’il acquiert un niveau dans une &lt;a class=&quot;pagelink&quot; href=&quot;Progression-Des-Personnages.html#CLASSEDEPREDILECTION&quot; title=&quot;Progression des personnages&quot;&gt;classe de pr&#233;dilection&lt;/a&gt;, un elfe peut choisir entre un certain nombre d’autres avantages d&#233;pendant de sa &lt;a class=&quot;pagelink&quot; href=&quot;Progression-Des-Personnages.html#CLASSEDEPREDILECTION&quot; title=&quot;Progression des personnages&quot;&gt;classe de pr&#233;dilection&lt;/a&gt;. Les options qui suivent sont disponibles &#224; tous les elfes qui poss&#232;dent la classe cit&#233;e comme &lt;a class=&quot;pagelink&quot; href=&quot;Progression-Des-Personnages.html#CLASSEDEPREDILECTION&quot; title=&quot;Progression des personnages&quot;&gt;classe de pr&#233;dilection&lt;/a&gt; et, sauf mention contraire, le bonus s’applique chaque fois qu’il choisit l’avantage en question.&lt;br /&gt;&lt;br /&gt;&lt;table class=&quot;page espace-col deuxcol&quot;&gt;&lt;tr&gt;&lt;td&gt;
&lt;b&gt;&lt;a class=&quot;pagelink&quot; href=&quot;Alchimiste.html&quot; title=&quot;L&amp;#39;alchimiste&quot;&gt;Alchimiste&lt;/a&gt;.&lt;/b&gt; Les elfes pr&#233;f&#232;rent les disciplines magiques classiques aux exp&#233;rimentations et &#224; la pseudo-science de l’alchimie, qu’ils d&#233;peignent souvent comme une grossi&#232;re imitation de la magie traditionnelle. Les &lt;a class=&quot;pagelink&quot; href=&quot;Alchimiste.html&quot; title=&quot;L&amp;#39;alchimiste&quot;&gt;alchimistes&lt;/a&gt; elfes choisissent souvent la vie d’aventuriers afin d’&#233;chapper au m&#233;pris de leurs pairs.&lt;br /&gt;&lt;br /&gt;&lt;b&gt;&lt;a class=&quot;pagelink&quot; href=&quot;Barbare.html&quot; title=&quot;Le barbare&quot;&gt;Barbare&lt;/a&gt;.&lt;/b&gt; Les &lt;a class=&quot;pagelink&quot; href=&quot;Barbare.html&quot; title=&quot;Le barbare&quot;&gt;barbares&lt;/a&gt; elfes vivent g&#233;n&#233;ralement dans les profondeurs des d&#233;serts ou des jungles sous la guidance d’anciens sages et mystiques. Lorsqu’ils quittent leur patrie, c’est souvent pour accomplir une mission pour leur peuple ou pour d&#233;couvrir le monde ext&#233;rieur.&lt;br /&gt;&lt;br /&gt;&lt;i&gt;Bonus de classe de pr&#233;dilection alternatif.&lt;/i&gt; Ajouter 30 cm &#224; la &lt;a class=&quot;pagelink&quot; href=&quot;Elfe.html#VITESSENORMALE&quot; title=&quot;Les elfes&quot;&gt;vitesse de base&lt;/a&gt; de l’elfe. En combat, cela n’a aucun effet &#224; moins que l’elfe ait choisi cet avantage 5 fois (ou un autre multiple de 5). La vitesse est arrondie au multiple de 1,50 m inf&#233;rieur, de sorte qu’une vitesse de 10,20 m est la m&#234;me qu’une vitesse de 9 m par exemple. Ce bonus se cumule avec la capacit&#233; de &lt;a class=&quot;pagelink&quot; href=&quot;Barbare.html#DEPLACEMENTACCELERE&quot; title=&quot;Le barbare&quot;&gt;d&#233;placement acc&#233;l&#233;r&#233;&lt;/a&gt; et s’applique sous les m&#234;mes conditions que celle-ci.&lt;br /&gt;&lt;br /&gt;&lt;b&gt;&lt;a class=&quot;pagelink&quot; href=&quot;Barde.html&quot; title=&quot;Le barde&quot;&gt;Barde&lt;/a&gt;.&lt;/b&gt; Les elfes aiment l’art sous toutes ses formes. Les envol&#233;es de leurs arias, leurs po&#233;sies anciennes et leurs danses gracieuses sont envi&#233;es par tous les publics cultiv&#233;s,tout comme leur panache au combat suscite l’envie de la plupart des &lt;a class=&quot;pagelink&quot; href=&quot;Guerrier.html&quot; title=&quot;Le guerrier&quot;&gt;guerriers&lt;/a&gt;.&lt;br /&gt;&lt;br /&gt;&lt;i&gt;Bonus de classe de pr&#233;dilection alternatif.&lt;/i&gt; Ajouter +1 au &lt;a class=&quot;pagelink&quot; href=&quot;Manœuvres-Offensives.html#DMD&quot; title=&quot;DMD&quot;&gt;DMD&lt;/a&gt; de l’elfe contre le &lt;a class=&quot;pagelink&quot; href=&quot;Manœuvres-Offensives.html#DESARMEMENT&quot; title=&quot;Les manœuvres de combat&quot;&gt;d&#233;sarmement&lt;/a&gt; et la &lt;a class=&quot;pagelink&quot; href=&quot;Manœuvres-Offensives.html#DESTRUCTION&quot; title=&quot;Les manœuvres de combat&quot;&gt;destruction d&#39;objets&lt;/a&gt;.&lt;br /&gt;&lt;br /&gt;&lt;b&gt;&lt;a class=&quot;pagelink&quot; href=&quot;Chevalier.html&quot; title=&quot;Le chevalier&quot;&gt;Chevalier&lt;/a&gt;.&lt;/b&gt; Les &lt;a class=&quot;pagelink&quot; href=&quot;Chevalier.html&quot; title=&quot;Le chevalier&quot;&gt;chevaliers&lt;/a&gt; elfes sont issus d’une longue tradition au sein des anciennes maisons nobles. Ils cherchent &#224; gagner et &#224; d&#233;fendre leur honneur avec &#233;l&#233;gance. Leurs &lt;a class=&quot;pagelink&quot; href=&quot;Chevalier.html#MONTURE&quot; title=&quot;Le chevalier&quot;&gt;montures&lt;/a&gt; agiles sont &#224; la fois tr&#232;s r&#233;sistantes et tr&#232;s fid&#232;les.&lt;br /&gt;&lt;br /&gt;&lt;i&gt;Bonus de classe de pr&#233;dilection alternatif.&lt;/i&gt; Ajouter +1 point de vie &#224; la &lt;a class=&quot;pagelink&quot; href=&quot;Chevalier.html#MONTURE&quot; title=&quot;Le chevalier&quot;&gt;monture du chevalier&lt;/a&gt;. Si l’elfe change de &lt;a class=&quot;pagelink&quot; href=&quot;Chevalier.html#MONTURE&quot; title=&quot;Le chevalier&quot;&gt;monture&lt;/a&gt;, la nouvelle b&#233;n&#233;ficie de ces points de vie suppl&#233;mentaires. Cela ne s’applique qu’&#224; une seule &lt;a class=&quot;pagelink&quot; href=&quot;Chevalier.html#MONTURE&quot; title=&quot;Le chevalier&quot;&gt;monture&lt;/a&gt;, celle gagn&#233;e au fil de l’&#233;volution dans la classe de &lt;a class=&quot;pagelink&quot; href=&quot;Chevalier.html&quot; title=&quot;Le chevalier&quot;&gt;chevalier&lt;/a&gt;.&lt;br /&gt;&lt;br /&gt;&lt;b&gt;&lt;a class=&quot;pagelink&quot; href=&quot;Conjurateur.html&quot; title=&quot;Le conjurateur (aussi appel&#233; invocateur)&quot;&gt;Conjurateur&lt;/a&gt;.&lt;/b&gt; Gr&#226;ce &#224; leur affinit&#233; avec les arts mystiques, les elfes poss&#232;dent une longue tradition d’alliance avec des cr&#233;atures magiques. M&#234;me si les &lt;a class=&quot;pagelink&quot; href=&quot;Conjurateur.html&quot; title=&quot;Le conjurateur (aussi appel&#233; invocateur)&quot;&gt;conjurateurs&lt;/a&gt; elfes sont moins nombreux que les &lt;a class=&quot;pagelink&quot; href=&quot;Ensorceleur.html&quot; title=&quot;L&amp;#39;ensorceleur&quot;&gt;ensorceleurs&lt;/a&gt; ou les &lt;a class=&quot;pagelink&quot; href=&quot;Magicien.html&quot; title=&quot;Le magicien&quot;&gt;magiciens&lt;/a&gt;, ils sont bien repr&#233;sent&#233;s au sein des arm&#233;es elfiques. Leur &lt;a class=&quot;pagelink&quot; href=&quot;Eidolon.html&quot; title=&quot;L&amp;#39;&#233;idolon du conjurateur&quot;&gt;eidolons&lt;/a&gt; sont souvent des cr&#233;atures translucides qui paraissent beaucoup moins fortes et puissantes qu’elles ne le sont r&#233;ellement.&lt;br /&gt;&lt;br /&gt;&lt;b&gt;&lt;a class=&quot;pagelink&quot; href=&quot;Druide.html&quot; title=&quot;Le druide&quot;&gt;Druide&lt;/a&gt;.&lt;/b&gt; Les elfes poss&#232;dent un lien instinctif avec la nature et les esprits myst&#233;rieux qui l’habitent. Certains d’entre eux vont jusqu’&#224; v&#233;n&#233;rer ces puissances en s’attachant les services des forces de la nature et vice-versa.&lt;br /&gt;&lt;br /&gt;&lt;b&gt;&lt;a class=&quot;pagelink&quot; href=&quot;Ensorceleur.html&quot; title=&quot;L&amp;#39;ensorceleur&quot;&gt;Ensorceleur&lt;/a&gt;.&lt;/b&gt; La magie infuse le sang des elfes, de sorte que tous les &lt;a class=&quot;pagelink&quot; href=&quot;Lignages.html&quot; title=&quot;Les lignages d&amp;#39;ensorceleurs&quot;&gt;lignages d’ensorceleurs&lt;/a&gt; apparaissent au sein de leur peuple. Les &lt;a class=&quot;pagelink&quot; href=&quot;Ensorceleur.html&quot; title=&quot;L&amp;#39;ensorceleur&quot;&gt;ensorceleurs&lt;/a&gt; elfes ne sont toutefois pas aussi respect&#233;s que les &lt;a class=&quot;pagelink&quot; href=&quot;Magicien.html&quot; title=&quot;Le magicien&quot;&gt;magiciens&lt;/a&gt;.&lt;br /&gt;&lt;br /&gt;&lt;i&gt;Bonus de classe de pr&#233;dilection alternatif.&lt;/i&gt; Choisir un pouvoir de &lt;a class=&quot;pagelink&quot; href=&quot;Lignages.html&quot; title=&quot;Les lignages d&amp;#39;ensorceleurs&quot;&gt;lignage&lt;/a&gt; de niveau 1 qui est normalement utilisable un nombre de fois par jour &#233;gal &#224; 3 + le modificateur de &lt;a class=&quot;pagelink&quot; href=&quot;Caract&#233;ristiques.html#CHARISME&quot; title=&quot;Le Charisme&quot;&gt;Charisme&lt;/a&gt; de l’elfe. L’ensorceleur ajoute +1/2 au nombre d’utilisations quotidiennes de ce pouvoir de &lt;a class=&quot;pagelink&quot; href=&quot;Lignages.html&quot; title=&quot;Les lignages d&amp;#39;ensorceleurs&quot;&gt;lignage&lt;/a&gt;.&lt;br /&gt;&lt;br /&gt;&lt;b&gt;&lt;a class=&quot;pagelink&quot; href=&quot;Guerrier.html&quot; title=&quot;Le guerrier&quot;&gt;Guerrier&lt;/a&gt;.&lt;/b&gt; Les &lt;a class=&quot;pagelink&quot; href=&quot;Guerrier.html&quot; title=&quot;Le guerrier&quot;&gt;guerriers&lt;/a&gt; elfes sont respect&#233;s pour leur posture agile, leur pr&#233;cision d&#233;licate mais mortelle et leur ma&#238;trise de traditions martiales datant de plusieurs si&#232;cles.&lt;br /&gt;&lt;br /&gt;&lt;i&gt;Bonus de classe de pr&#233;dilection alternatif.&lt;/i&gt; Ajouter +1 au &lt;a class=&quot;pagelink&quot; href=&quot;Manœuvres-Offensives.html#DMD&quot; title=&quot;DMD&quot;&gt;DMD&lt;/a&gt; de l’elfe contre le &lt;a class=&quot;pagelink&quot; href=&quot;Manœuvres-Offensives.html#DESARMEMENT&quot; title=&quot;Les manœuvres de combat&quot;&gt;d&#233;sarmement&lt;/a&gt; et la &lt;a class=&quot;pagelink&quot; href=&quot;Manœuvres-Offensives.html#DESTRUCTION&quot; title=&quot;Les manœuvres de combat&quot;&gt;destruction d&#39;objets&lt;/a&gt;.
&lt;/td&gt;&lt;td&gt;
&lt;b&gt;&lt;a class=&quot;pagelink&quot; href=&quot;Inquisiteur.html&quot; title=&quot;L&amp;#39;inquisiteur&quot;&gt;Inquisiteur&lt;/a&gt;.&lt;/b&gt; M&#234;me si, en tant que race, les elfes accordent une grande importance &#224; la libert&#233; et aux individus, ils sont &#233;galement tr&#232;s traditionalistes et plut&#244;t m&#233;fiants &#224; l’&#233;gard des &#233;trangers. Les inquisiteurs elfes ne sont pas tr&#232;s appr&#233;ci&#233;s, mais leurs &lt;a class=&quot;pagelink&quot; href=&quot;Jugements.html&quot; title=&quot;Les jugements d&amp;#39;inquisiteur&quot;&gt;jugements&lt;/a&gt; et leur autorit&#233; sont respect&#233;s.&lt;br /&gt;&lt;br /&gt;&lt;b&gt;&lt;a class=&quot;pagelink&quot; href=&quot;Magicien.html&quot; title=&quot;Le magicien&quot;&gt;Magicien&lt;/a&gt;.&lt;/b&gt; Les elfes entretiennent une ancienne tradition de savoir et de recherche magique dans tous les domaines de sp&#233;cialisation possibles. Pour ceux qui poss&#232;dent un talent suffisant, la magie est l’une des voies d’acc&#232;s les plus s&#251;res vers une position prestigieuse au sein de la soci&#233;t&#233; elfique.&lt;br /&gt;&lt;br /&gt;&lt;i&gt;Bonus de classe de pr&#233;dilection alternatif.&lt;/i&gt; Choisir un pouvoir d’&lt;a class=&quot;pagelink&quot; href=&quot;&#201;coles-De-Magie.html&quot; title=&quot;Les &#233;coles de magie&quot;&gt;&#233;cole magique&lt;/a&gt; de niveau 1 qui est normalement utilisable un nombre de fois par jour &#233;gal &#224; 3 + le modificateur d’&lt;a class=&quot;pagelink&quot; href=&quot;Caract&#233;ristiques.html#INTELLIGENCE&quot; title=&quot;L&amp;#39;Intelligence&quot;&gt;Intelligence&lt;/a&gt; de l’elfe. Le &lt;a class=&quot;pagelink&quot; href=&quot;Magicien.html&quot; title=&quot;Le magicien&quot;&gt;magicien&lt;/a&gt; ajoute +1/2 au nombre d’utilisations quotidiennes de ce pouvoir.&lt;br /&gt;&lt;br /&gt;&lt;b&gt;&lt;a class=&quot;pagelink&quot; href=&quot;Moine.html&quot; title=&quot;Le moine&quot;&gt;Moine&lt;/a&gt;.&lt;/b&gt; Les elfes sont contemplatifs par nature et ils appr&#233;cient ceux qui s’int&#233;ressent au calme int&#233;rieur et &#224; la paix de l’esprit. Les &lt;a class=&quot;pagelink&quot; href=&quot;Moine.html&quot; title=&quot;Le moine&quot;&gt;moines&lt;/a&gt; elfes se laissent souvent guider par des mantras tr&#232;s anciens ou des exemples naturels d’&#233;quilibre et de finesse.&lt;br /&gt;&lt;br /&gt;&lt;b&gt;&lt;a class=&quot;pagelink&quot; href=&quot;Oracle.html&quot; title=&quot;L&amp;#39;oracle&quot;&gt;Oracle&lt;/a&gt;.&lt;/b&gt; Les &lt;a class=&quot;pagelink&quot; href=&quot;Oracle.html&quot; title=&quot;L&amp;#39;oracle&quot;&gt;oracles&lt;/a&gt; elfes sont assez r&#233;pandus et tr&#232;s respect&#233;s en tant que gardiens des &lt;a class=&quot;pagelink&quot; href=&quot;Myst&#232;res.html&quot; title=&quot;Les myst&#232;res d&amp;#39;oracle&quot;&gt;myst&#232;res&lt;/a&gt; de leurs anc&#234;tres et de secrets qui datent d’avant la venue au monde des innombrables races plus jeunes.&lt;br /&gt;&lt;br /&gt;&lt;b&gt;&lt;a class=&quot;pagelink&quot; href=&quot;Paladin.html&quot; title=&quot;Le paladin&quot;&gt;Paladin&lt;/a&gt;.&lt;/b&gt; Les &lt;a class=&quot;pagelink&quot; href=&quot;Paladin.html&quot; title=&quot;Le paladin&quot;&gt;paladins&lt;/a&gt; elfes adoptent et font respecter les &#233;dits ancestraux de leurs &lt;a class=&quot;pagelink&quot; href=&quot;../Golarion/Religions-Et-Philosophies.html&quot; title=&quot;Religions et philosophies&quot;&gt;divinit&#233;s&lt;/a&gt;. Ils prot&#232;gent leur peuple et leur contr&#233;e contre tous ceux qui voudraient profaner leurs terres sacr&#233;es.&lt;br /&gt;&lt;br /&gt;&lt;b&gt;&lt;a class=&quot;pagelink&quot; href=&quot;Pr&#234;tre.html&quot; title=&quot;Le pr&#234;tre&quot;&gt;Pr&#234;tre&lt;/a&gt;.&lt;/b&gt; Les elfes v&#233;n&#232;rent de nombreux &lt;a class=&quot;pagelink&quot; href=&quot;../Golarion/Religions-Et-Philosophies.html&quot; title=&quot;Religions et philosophies&quot;&gt;dieux&lt;/a&gt;. Leur long&#233;vit&#233; am&#232;ne de nombreux elfes &#224; se consid&#233;rer comme b&#233;nis des &lt;a class=&quot;pagelink&quot; href=&quot;../Golarion/Religions-Et-Philosophies.html&quot; title=&quot;Religions et philosophies&quot;&gt;dieux&lt;/a&gt;. Un bon nombre d’entre eux se tournent vers des philosophies naturalistes ou d’anciens patrons divins qui incarnent les traits caract&#233;ristiques de leur peuple.&lt;br /&gt;&lt;br /&gt;&lt;b&gt;&lt;a class=&quot;pagelink&quot; href=&quot;R&#244;deur.html&quot; title=&quot;Le r&#244;deur&quot;&gt;R&#244;deur&lt;/a&gt;.&lt;/b&gt; Les elfes sont des chasseurs et des &#233;claireurs hors pairs en harmonie avec leur environnement, attentifs &#224; tout ce qui les entoure et toujours pr&#234;ts &#224; prot&#233;ger leurs terres ou
&#224; punir les intrus. &lt;br /&gt;&lt;br /&gt;&lt;i&gt;Bonus de classe de pr&#233;dilection alternatif.&lt;/i&gt; Choisir une arme parmi la liste suivante : arc court, arc long, &#233;p&#233;e courte, &#233;p&#233;e longue, rapi&#232;re, ou n’importe quelle arme dont le nom comporte &#171; elfe &#187; ou &#171; elfique &#187;. Ajouter un bonus de circonstances de +1/2 aux jets de confirmation des &lt;a class=&quot;pagelink&quot; href=&quot;Actions-Simples.html#COUPCRITIQUE&quot; title=&quot;Actions simples&quot;&gt;critiques&lt;/a&gt; avec cette arme ( jusqu’&#224; un maximum de +4). Ce bonus ne se cumule pas avec celui offert par &lt;a class=&quot;pagelink&quot; href=&quot;Don-Pour-Les-Critiques.html&quot; title=&quot;Don pour les critiques&quot;&gt;Don pour les critiques&lt;/a&gt;.&lt;br /&gt;&lt;br /&gt;&lt;b&gt;&lt;a class=&quot;pagelink&quot; href=&quot;Roublard.html&quot; title=&quot;Le roublard&quot;&gt;Roublard&lt;/a&gt;.&lt;/b&gt; M&#234;me si les voleurs, les brigands et autres vauriens sont rares dans la soci&#233;t&#233; elfe, les elfes &lt;a class=&quot;pagelink&quot; href=&quot;Roublard.html&quot; title=&quot;Le roublard&quot;&gt;roublards&lt;/a&gt; sont aussi nombreux que les &#233;claireurs, les espions et m&#234;me les assassins.&lt;br /&gt;&lt;br /&gt;&lt;b&gt;&lt;a class=&quot;pagelink&quot; href=&quot;Sorci&#232;re.html&quot; title=&quot;La sorci&#232;re&quot;&gt;Sorci&#232;re&lt;/a&gt;.&lt;/b&gt; En concluant des pactes avec des puissances &#233;ternelles et invisibles, les &lt;a class=&quot;pagelink&quot; href=&quot;Sorci&#232;re.html&quot; title=&quot;La sorci&#232;re&quot;&gt;sorci&#232;re&lt;/a&gt;s elfes combinent leur compr&#233;hension de la nature et leur ma&#238;trise de la magie pour en tirer de puissants
&lt;a class=&quot;pagelink&quot; href=&quot;Mal&#233;fices.html&quot; title=&quot;Les mal&#233;fices de sorci&#232;res&quot;&gt;mal&#233;fices&lt;/a&gt; et des arcanes &#233;tranges. Nombre d’entre elles tissent des liens avec les cr&#233;atures qui habitent leur r&#233;gion et les adoptent comment &lt;a class=&quot;pagelink&quot; href=&quot;Familiers.html&quot; title=&quot;Les familiers&quot;&gt;familiers&lt;/a&gt; pour renforcer leur connexion avec la terre.
&lt;/td&gt;&lt;/tr&gt;&lt;/table&gt;
]]></body>
  <raw><![CDATA[{s:MenuRaces}''Les elfes sont des créatures de la nature qui possèdent de nombreux points communs (et quelques différences) avec les créatures féeriques. Les elfes accordent beaucoup d’importance à l’intimité et aux traditions. Ils n’accordent pas leur amitié rapidement mais, lorsqu’un elfe ou une communauté d’elfes considère un étranger comme un camarade, cette alliance peut perdurer sur plusieurs générations. À cause de leur espérance de vie incroyablement longue ou peut-être pour des raisons plus mystiques, les elfes possèdent une relation étrange avec leur environnement. Ceux qui résident dans une région pendant une longue période subissent une adaptation physique à leur milieu, dont l’aspect le plus flagrant est un changement de couleur de peau. De leur côté, les elfes qui passent leur vie au sein des autres races à moindre espérance de vie développent souvent une perception faussée de la mortalité et deviennent moroses après avoir assisté de manière répétée au vieillissement et à la mort de leurs compagnons.''

<div class="presentation arrondi">
{s:APG}Connus pour leur grâce, leur sagesse et leur quasi-immortalité, les elfes sont tenus en haute estime par la plupart des autres races, tout spécialement pour leur maîtrise de la magie et leur savoir encyclopédique. Cependant, les membres de cette race se sentent souvent cernés de toutes parts et isolés par des races plus jeunes, plus agressives et comptant beaucoup plus d’individus qu’eux. Malgré tout, les aventuriers elfes qui ont été élevés et ont grandi dans des enclaves elfiques qui, bien souvent, incarnent
la beauté et l’esprit de leur environnement, emportent avec eux la force et la gloire de la culture elfique et les répandent dans le monde, souvent par l’épée ou à l’aide de la magie. La vision classique des elfes en tant que protecteurs des forêts est correcte mais incomplète : les elfes s’adaptent facilement à de nombreux environnements pouvant aller des déserts les plus inhospitaliers aux profondeurs de la mer. D’autres s’intéressent aux mystères et à la magie de certains domaines que leurs
frères et soeurs ignorent. Ces elfes possèdent des traits raciaux différents de ceux dont jouissent les individus élevés dans un style de vie elfique plus traditionnel.
</div>

'''Description physique.''' Les elfes sont généralement plus grands que les humains, mais aussi plus gracieux et plus fragiles (une apparence que leurs longues oreilles pointues accentuent). Ils possèdent de larges yeux en forme d’amande et de grandes pupilles de couleur vive. Les elfes se parent généralement d’habits qui rappellent la beauté de la nature, mais ceux qui vivent en ville s’habillent plutôt selon la mode en vogue.

'''Société.''' De nombreux elfes se sentent fortement liés à la nature et tentent de vivre en harmonie avec elle. Le travail de la terre et de la pierre n’en attire cependant pas beaucoup : ils préfèrent s’adonner à des arts plus raffinés. Leur patience innée les destine naturellement à une carrière dans les arts magiques.

'''Relations.''' Les elfes ont tendance à considérer les autres races comme trop impulsives et irréfléchies et à les rejeter. Ils sont cependant très doués pour cerner les personnalités et les qualités. Un elfe évitera de prendre un [[nain]] pour voisin mais il sera le premier à reconnaître son habileté à la forge. Ils voient les [[gnome|gnomes]] comme des curiosités étranges (et parfois même dangereuses) et éprouvent une certaine pitié envers les [[halfelin|halfelins]] car les petites gens leur semblent dépourvus d’attaches et de foyer originel. Les [[humain|humains]], quant à eux, fascinent les elfes. Le nombre important de [[demi-elfe|demi-elfes]] en est la preuve, même si les elfes ne s’attachent généralement pas à leurs descendants. Quant aux [[demi-orque|demi-orques]], ils leur inspirent de la méfiance.

'''Alignement et religion.''' Les elfes se laissent guider par les émotions et les caprices mais ils accordent une grande importance à la gentillesse et à la beauté. La plupart des elfes sont d’[[alignement]] [[CB|Chaotique Bon]]. Ils préfèrent les dieux qui partagent leur amour du mysticisme.

'''Aventuriers.''' La plupart des elfes qui partent à l’aventure sont mus par le désir d’explorer le monde. Ils quittent leurs royaumes forestiers isolés à la recherche d’anciennes magies elfiques ou des empires oubliés fondés par leurs ancêtres des millénaires plus tôt. Le côté éphémère de la vie d’aventurier et la liberté qui la caractérise attirent naturellement les elfes qui ont été élevés au sein des communautés humaines. À cause de leur fragilité physique, les elfes évitent généralement le combat au corps à corps et préfèrent se tourner vers des classes comme [[magicien]] ou [[rôdeur]].

===Les traits raciaux des elfes===

<table class="page espace-col deuxcol">
<tr style="vertical-align: top"><td>
<div class="presentation arrondi ombre espaceliste">
===Traits raciaux des elfes===

* '''+2 [[Dextérité]], +2 [[Intelligence]], -2 [[Constitution]].''' Les elfes sont agiles, tant physiquement que mentalement, mais plutôt frêles.
* '''Taille moyenne.''' Les elfes sont des créatures de [[taille M]], ce qui ne leur apporte aucun bonus ni malus de taille.
{s:Reference|VITESSENORMALE}
* '''Vitesse normale.''' Les elfes possèdent une [[vitesse de déplacement]] de base de 9 mètres (6 cases).
* '''[[Vision nocturne]].''' Les elfes peuvent voir deux fois plus loin que les humains dans des conditions de faible éclairage.
* '''Immunités elfiques.''' Les elfes sont immunisés aux effets de sommeil magique et bénéficient d’un bonus racial de +2 aux [[jet de sauvegarde|jets de sauvegarde]] contre les sorts et les effets de type [[enchantement]].
* '''Magie elfique.''' Les elfes reçoivent un bonus racial de +2 aux tests de [[NLS|niveau de lanceur de sorts]] pour surmonter la [[RM|résistance à la magie]] des cibles. Ils reçoivent également un bonus racial de +2 aux tests d’[[Art de la magie]] pour identifier les propriétés des objets magiques.
* '''Sens aiguisés.''' Les elfes reçoivent un bonus racial de +2 aux tests de [[Perception]].
* '''Armes familières.''' Les elfes sont formés au maniement des arcs longs (y compris les arcs longs composites), des arcs courts (y compris les arcs courts composites), des épées longues, des rapières et ils considèrent toutes les armes dont le nom comporte le mot « elfe » ou « elfique » comme des [[arme de guerre|armes de guerre]].
* '''Langues supplémentaires.''' Les elfes connaissent automatiquement le [[Linguistique|commun]] et l’[[Linguistique|elfe]]. Les elfes possédant une [[Intelligence]] élevée peuvent choisir d’[[Linguistique|autres langues]] parmi la liste suivante : [[Linguistique|céleste]], [[Linguistique|draconien]], [[Linguistique|gnoll]], [[Linguistique|gnome]], [[Linguistique|gobelin]], [[Linguistique|orque]] et [[Linguistique|sylvestre]].

</div>
</td><td>
<div class="presentation arrondi ombre espaceliste">{s:APG}
===Traits alternatifs===
* '''Agent de la lumière.''' Certains elfes vénèrent le soleil, la lune et les étoiles, mais d’autres sont littéralement touchés par le pouvoir radieux des cieux. Les elfes disposant de ce trait racial sont immunisés contre l’[[États préjudiciables#Aveuglé|aveuglement]] par la lumière et les effets [[États préjudiciables#Ébloui|éblouissants]]. De plus, lorsqu’ils lancent des sorts ou des effets basés sur la lumière (y compris les [[capacités spéciales#TYPES|pouvoirs magiques]] et les [[capacités spéciales#TYPES|capacités surnaturelles]]), les variables de ceux-ci sont déterminées comme s’ils avaient un niveau de plus. Les elfes possédant une [[Intelligence]] supérieure ou égale à 10 peuvent utiliser [[lumière]] à volonté en tant que [[capacités spéciales#types|pouvoir magique]]. Ce trait racial remplace Immunités elfiques et Magie elfique.
* '''Chasseur silencieux.''' Les elfes sont réputés pour leur subtilité et leurs prouesses. Les elfes disposant de ce trait racial réduisent de 5 la pénalité imposée aux tests de [[Discrétion]] effectués au cours d’un déplacement et peuvent effectuer de tels tests même en courant, avec une pénalité de -20 (ce nombre inclut la réduction de pénalité offerte par ce trait). Ce trait racial remplace Magie elfique.
* '''Coureur du désert.''' Certains elfes s’efforcent de survivre dans les profondeurs du désert où ils ne cessent de parcourir des terres brûlées et desséchées. Les elfes disposant de ce trait racial gagnent un bonus racial de +4 aux tests de [[Constitution]] et aux jets de [[Valeurs de combat#JETDESAUVEGARDE|Vigueur]] pour éviter la fatigue, l’épuisement ou les autres effets négatifs de la course, des marches forcées, de la faim, de la soif et des environnements chauds ou froids. Ce trait racial remplace Magie elfique.
* '''Esprit des eaux.''' Certains elfes se sont adaptés à une vie en harmonie avec la mer ou les profondeurs des rivières et des lacs sauvages. Ils gagnent un bonus racial de +4 aux tests de [[Natation]], peuvent toujours [[compétences#FAIRE10|« faire 10 »]] pour nager et peuvent choisir l’aquatique comme [[linguistique|langue supplémentaire]]. Ils sont formés au maniement de la pique, du trident et du filet. Ce trait racial remplace Magie elfique et Armes familières.
* '''Murmures des rêves.''' Certains elfes sont capables d’utiliser le pouvoir du sommeil, des rêves et de la rêverie précognitive. Les elfes disposant de ce trait racial ajoutent +1 aux [[Vocabulaire courant#DEGREDEDIFFICULTE|DD]] des [[Valeurs de combat#JETDESAUVEGARDE|jets de sauvegarde]] des sorts de l’[[Divination (école)|école de Divination]] et des effets de sommeil qu’ils lancent. De plus, ceux qui possèdent un [[Charisme]] supérieur ou égal à 15 peuvent utiliser [[songe]] une fois par jour sous la forme d’un [[capacités spéciales#TYPES|pouvoir magique]] dont le [[Lancer des sorts#NLS|NLS]] est égal au niveau de personnage. Ce trait racial remplace Immunités elfiques.
* '''Rancune éternelle.''' Les elfes disposant de ce trait racial ont grandi dans des communautés isolées et isolationnistes où des querelles datant de plusieurs générations ont donné naissance à des conflits sanglants perpétuels. Ils reçoivent un bonus de +1 aux [[Valeurs de combat#JETDATTAQUE|jets d’attaque]] contre les humanoïdes des sous-types [[nain]] et [[orque]] grâce à un entraînement spécial contre ces adversaires. Ce trait racial remplace
Magie elfique.
* '''Travail du bois.''' Les elfes connaissent mieux que quiconque les secrets des contrées sauvages et plus particulièrement des forêts. Les elfes disposant de ce trait racial gagnent un bonus de +1 aux tests de [[Connaissances]] (nature) et aux tests de [[Survie]]. En forêt, ces bonus passent à +2. Ce trait racial remplace Magie elfique.

</div>
</td></tr></table>

{s:APG}
=== Les aventuriers elfes ===

Les elfes qui choisissent de devenir aventuriers suivent généralement la voie du combattant, cherchent à maîtriser la magie profane ou optent pour une carrière qui mélangent les deux. Les elfes préfèrent la subtilité au conflit ouvert mais ils aiment démontrer leur supériorité aux autres races, quitte à employer la force si la finesse et le panache ne suffisent pas.

''Bonus de classe de prédilection alternatif:'' Plutôt que de gagner un point de vie ou un point de compétence supplémentaire lorsqu’il acquiert un niveau dans une [[Progression des personnages#CLASSEDEPREDILECTION|classe de prédilection]], un elfe peut choisir entre un certain nombre d’autres avantages dépendant de sa [[Progression des personnages#CLASSEDEPREDILECTION|classe de prédilection]]. Les options qui suivent sont disponibles à tous les elfes qui possèdent la classe citée comme [[Progression des personnages#CLASSEDEPREDILECTION|classe de prédilection]] et, sauf mention contraire, le bonus s’applique chaque fois qu’il choisit l’avantage en question.

<table class="page espace-col deuxcol"><tr><td>
'''[[Alchimiste]].''' Les elfes préfèrent les disciplines magiques classiques aux expérimentations et à la pseudo-science de l’alchimie, qu’ils dépeignent souvent comme une grossière imitation de la magie traditionnelle. Les [[alchimiste|alchimistes]] elfes choisissent souvent la vie d’aventuriers afin d’échapper au mépris de leurs pairs.

'''[[Barbare]].''' Les [[barbare|barbares]] elfes vivent généralement dans les profondeurs des déserts ou des jungles sous la guidance d’anciens sages et mystiques. Lorsqu’ils quittent leur patrie, c’est souvent pour accomplir une mission pour leur peuple ou pour découvrir le monde extérieur.

''Bonus de classe de prédilection alternatif.'' Ajouter 30 cm à la [[elfe#VITESSENORMALE|vitesse de base]] de l’elfe. En combat, cela n’a aucun effet à moins que l’elfe ait choisi cet avantage 5 fois (ou un autre multiple de 5). La vitesse est arrondie au multiple de 1,50 m inférieur, de sorte qu’une vitesse de 10,20 m est la même qu’une vitesse de 9 m par exemple. Ce bonus se cumule avec la capacité de [[barbare#DEPLACEMENTACCELERE|déplacement accéléré]] et s’applique sous les mêmes conditions que celle-ci.

'''[[Barde]].''' Les elfes aiment l’art sous toutes ses formes. Les envolées de leurs arias, leurs poésies anciennes et leurs danses gracieuses sont enviées par tous les publics cultivés,tout comme leur panache au combat suscite l’envie de la plupart des [[guerrier|guerriers]].

''Bonus de classe de prédilection alternatif.'' Ajouter +1 au [[DMD]] de l’elfe contre le [[Manœuvres offensives#DESARMEMENT|désarmement]] et la [[Manœuvres offensives#DESTRUCTION|destruction d'objets]].

'''[[Chevalier]].''' Les [[chevalier|chevaliers]] elfes sont issus d’une longue tradition au sein des anciennes maisons nobles. Ils cherchent à gagner et à défendre leur honneur avec élégance. Leurs [[chevalier#MONTURE|montures]] agiles sont à la fois très résistantes et très fidèles.

''Bonus de classe de prédilection alternatif.'' Ajouter +1 point de vie à la [[chevalier#MONTURE|monture du chevalier]]. Si l’elfe change de [[chevalier#MONTURE|monture]], la nouvelle bénéficie de ces points de vie supplémentaires. Cela ne s’applique qu’à une seule [[chevalier#MONTURE|monture]], celle gagnée au fil de l’évolution dans la classe de [[chevalier]].

'''[[Conjurateur]].''' Grâce à leur affinité avec les arts mystiques, les elfes possèdent une longue tradition d’alliance avec des créatures magiques. Même si les [[conjurateur|conjurateurs]] elfes sont moins nombreux que les [[ensorceleur|ensorceleurs]] ou les [[magicien|magiciens]], ils sont bien représentés au sein des armées elfiques. Leur [[eidolon|eidolons]] sont souvent des créatures translucides qui paraissent beaucoup moins fortes et puissantes qu’elles ne le sont réellement.

'''[[Druide]].''' Les elfes possèdent un lien instinctif avec la nature et les esprits mystérieux qui l’habitent. Certains d’entre eux vont jusqu’à vénérer ces puissances en s’attachant les services des forces de la nature et vice-versa.

'''[[Ensorceleur]].''' La magie infuse le sang des elfes, de sorte que tous les [[lignages|lignages d’ensorceleurs]] apparaissent au sein de leur peuple. Les [[ensorceleur|ensorceleurs]] elfes ne sont toutefois pas aussi respectés que les [[magicien|magiciens]].

''Bonus de classe de prédilection alternatif.'' Choisir un pouvoir de [[lignages|lignage]] de niveau 1 qui est normalement utilisable un nombre de fois par jour égal à 3 + le modificateur de [[Charisme]] de l’elfe. L’ensorceleur ajoute +1/2 au nombre d’utilisations quotidiennes de ce pouvoir de [[lignages|lignage]].

'''[[Guerrier]].''' Les [[guerrier|guerriers]] elfes sont respectés pour leur posture agile, leur précision délicate mais mortelle et leur maîtrise de traditions martiales datant de plusieurs siècles.

''Bonus de classe de prédilection alternatif.'' Ajouter +1 au [[DMD]] de l’elfe contre le [[Manœuvres offensives#DESARMEMENT|désarmement]] et la [[Manœuvres offensives#DESTRUCTION|destruction d'objets]].
</td><td>
'''[[Inquisiteur]].''' Même si, en tant que race, les elfes accordent une grande importance à la liberté et aux individus, ils sont également très traditionalistes et plutôt méfiants à l’égard des étrangers. Les inquisiteurs elfes ne sont pas très appréciés, mais leurs [[jugements]] et leur autorité sont respectés.

'''[[Magicien]].''' Les elfes entretiennent une ancienne tradition de savoir et de recherche magique dans tous les domaines de spécialisation possibles. Pour ceux qui possèdent un talent suffisant, la magie est l’une des voies d’accès les plus sûres vers une position prestigieuse au sein de la société elfique.

''Bonus de classe de prédilection alternatif.'' Choisir un pouvoir d’[[écoles de magie|école magique]] de niveau 1 qui est normalement utilisable un nombre de fois par jour égal à 3 + le modificateur d’[[Intelligence]] de l’elfe. Le [[magicien]] ajoute +1/2 au nombre d’utilisations quotidiennes de ce pouvoir.

'''[[Moine]].''' Les elfes sont contemplatifs par nature et ils apprécient ceux qui s’intéressent au calme intérieur et à la paix de l’esprit. Les [[moine|moines]] elfes se laissent souvent guider par des mantras très anciens ou des exemples naturels d’équilibre et de finesse.

'''[[Oracle]].''' Les [[oracle|oracles]] elfes sont assez répandus et très respectés en tant que gardiens des [[mystères]] de leurs ancêtres et de secrets qui datent d’avant la venue au monde des innombrables races plus jeunes.

'''[[Paladin]].''' Les [[paladin|paladins]] elfes adoptent et font respecter les édits ancestraux de leurs [[++Golarion.religions et philosophies|divinités]]. Ils protègent leur peuple et leur contrée contre tous ceux qui voudraient profaner leurs terres sacrées.

'''[[Prêtre]].''' Les elfes vénèrent de nombreux [[++Golarion.religions et philosophies|dieux]]. Leur longévité amène de nombreux elfes à se considérer comme bénis des [[++Golarion.religions et philosophies|dieux]]. Un bon nombre d’entre eux se tournent vers des philosophies naturalistes ou d’anciens patrons divins qui incarnent les traits caractéristiques de leur peuple.

'''[[Rôdeur]].''' Les elfes sont des chasseurs et des éclaireurs hors pairs en harmonie avec leur environnement, attentifs à tout ce qui les entoure et toujours prêts à protéger leurs terres ou
à punir les intrus. 

''Bonus de classe de prédilection alternatif.'' Choisir une arme parmi la liste suivante : arc court, arc long, épée courte, épée longue, rapière, ou n’importe quelle arme dont le nom comporte « elfe » ou « elfique ». Ajouter un bonus de circonstances de +1/2 aux jets de confirmation des [[actions simples#COUPCRITIQUE|critiques]] avec cette arme ( jusqu’à un maximum de +4). Ce bonus ne se cumule pas avec celui offert par [[Don pour les critiques]].

'''[[Roublard]].''' Même si les voleurs, les brigands et autres vauriens sont rares dans la société elfe, les elfes [[roublard|roublards]] sont aussi nombreux que les éclaireurs, les espions et même les assassins.

'''[[Sorcière]].''' En concluant des pactes avec des puissances éternelles et invisibles, les [[sorcière|sorcière]]s elfes combinent leur compréhension de la nature et leur maîtrise de la magie pour en tirer de puissants
[[maléfices]] et des arcanes étranges. Nombre d’entre elles tissent des liens avec les créatures qui habitent leur région et les adoptent comment [[familiers]] pour renforcer leur connexion avec la terre.
</td></tr></table>]]></raw>
  <fullName>Pathfinder-RPG.Elfe</fullName>
</wikiPage>